MANIFEST.in
README.rst
TITLE.txt
lh-agpl3-LICENSE.txt
setup.py
bisos2/__init__.py
bisos2.coreDist.egg-info/PKG-INFO
bisos2.coreDist.egg-info/SOURCES.txt
bisos2.coreDist.egg-info/dependency_links.txt
bisos2.coreDist.egg-info/namespace_packages.txt
bisos2.coreDist.egg-info/not-zip-safe
bisos2.coreDist.egg-info/requires.txt
bisos2.coreDist.egg-info/top_level.txt
bisos2/coreDist/__init__.py
bisos2/coreDist/thisPkg.py